DESCRIPTION.rst
LICENSE
MANIFEST.in
README.rst
setup.py
bash/xlines-completion.bash
config/directories.list
config/exclusions.list
xlines/__init__.py
xlines/_version.py
xlines/about.py
xlines/cli.py
xlines/colormap.py
xlines/colors.py
xlines/common.py
xlines/configure.py
xlines/core.py
xlines/exclusions.py
xlines/export.py
xlines/help_menu.py
xlines/logd.py
xlines/menu.py
xlines/mp.py
xlines/oscodes_unix.py
xlines/oscodes_win.py
xlines/square.py
xlines/statics.py
xlines/thread_progress.py
xlines/usermessage.py
xlines/variables.py