Metadata-Version: 1.2
Name: xlines
Version: 0.7.10
Summary: Count the number of lines of code in a project
Home-page: https://github.com/fstab50/xlines
Author: Blake Huber
Author-email: blakeca00@gmail.com
License: GPL-3.0
Keywords: code development tools
Platform: UNKNOWN
Classifier: Topic :: Software Development :: Build Tools
Classifier: Development Status :: 4 - Beta
Classifier: Programming Language :: Python :: 3.6
Classifier: Programming Language :: Python :: 3.7
Classifier: License :: OSI Approved :: GNU General Public License v3 (GPLv3)
Classifier: Operating System :: POSIX :: Linux
Requires-Python: >=3.6, <4
